elk/__about__.py
elk/__init__.py
elk/java_utils.py
elk/server.py
elk/types.py
elk_python-0.0.1.dist-info/METADATA
elk_python-0.0.1.dist-info/WHEEL
elk_python-0.0.1.dist-info/licenses/LICENSE.txt
elk_python-0.0.1.dist-info/RECORD
